RagSGE_chinese/__init__.py
RagSGE_chinese/compactjsonencoder.py
RagSGE_chinese/es_context_sort.py
RagSGE_chinese/eval_pipeline.py
RagSGE_chinese/gen_gt.py
RagSGE_chinese/main.py
RagSGE_chinese/ragas_eval.py
RagSGE_chinese-0.14.dist-info/METADATA
RagSGE_chinese-0.14.dist-info/WHEEL
RagSGE_chinese-0.14.dist-info/top_level.txt
RagSGE_chinese-0.14.dist-info/RECORD
