Metadata-Version: 2.1
Name: RagSGE_chinese
Version: 0.14
Requires-Dist: openai
Requires-Dist: langchain
Requires-Dist: langchain-openai
Requires-Dist: python-dotenv
Requires-Dist: elasticsearch (==8.8.2)
Requires-Dist: tqdm
Requires-Dist: scipy
Requires-Dist: tiktoken
Requires-Dist: pandas
Requires-Dist: datasets
Requires-Dist: ragas
Requires-Dist: openpyxl
